dexparser/__init__.py
dexparser/disassembler.py
dexparser/errors.py
dexparser/utils.py
tests/__init__.py
tests/test_load_dex.py
tests/test_multi_dex_aab.py
tests/test_multi_dex_apk.py
tests/test_parse_single_dex.py
tests/test_single_dex_aab.py
tests/test_single_dex_apk.py
dexparser-1.2.0.dist-info/LICENSE
dexparser-1.2.0.dist-info/METADATA
dexparser-1.2.0.dist-info/WHEEL
dexparser-1.2.0.dist-info/top_level.txt
dexparser-1.2.0.dist-info/RECORD
