Metadata-Version: 2.1
Name: dexparser
Version: 1.2.0
Summary: Powerful DEX file format parser for Pythonista
Home-page: https://github.com/bunseokbot/dexparser
Author: austinkim
Author-email: austin.njkim@gmail.com
Classifier: Programming Language :: Python :: 3
Classifier: Programming Language :: Python :: 3.5
Classifier: Programming Language :: Python :: 3.6
Classifier: Programming Language :: Python :: 3.7
Classifier: Programming Language :: Python :: 3.8
Classifier: Programming Language :: Python :: 3.9
Classifier: Programming Language :: Python :: 3.10
Classifier: License :: OSI Approved :: MIT License
Classifier: Operating System :: OS Independent
Requires-Python: >=3.5
License-File: LICENSE
